{
  "streamingList": [
    {
      "label": "Stream - 01",
      "title": "Germany Hamm Sivasri A.Paskara Kurugal & Srimathi Mathivani ammal  livetelecast",
      "date": "16.09.2023",
      "timeFrom": "15:00",
      "timeTo": " 18:00",
      "description": "Germany hamm  Manivela festival",
      "videoList": [{ "youtubeVideoID": "-WaDoNBvnmo" }, { "youtubeVideoID": "eventplayv2.page.link/kaneen" }]
    },
    
    {
      "label": "Stream - 03",
      "title": "Shoban Prabagaran & Kaveetheeni Kaneen from Malasiya Wedding late livetelecast",
      "date": "26.06.2022",
      "timeFrom": "12:30",
      "timeTo": " 14:00",
      "description": " Malasiya Murugan Kovel ",
      "videoList": [{ "youtubeVideoID": "INiO-3ikBd8" }, { "youtubeVideoID": "4" }]
    }        
    
  ],
  "historyList": [
    {
      "label": "Stream - 01",
      "title": "Shoban Prabagaran  from Australia & Kaveetheeni Kaneen- Reception livetelecast",
      "date": "02.04.2022",
      "timeFrom": "17:30",
      "timeTo": " 20:00",
      "description": " Germany Wuppertal Westfalenweg88-42111Wuppertal ",
      "videoList": [{ "youtubeVideoID": "O2f2S820VTo" }, { "youtubeVideoID": "0" }]
    },
    {
      "label": "Stream - 01",
      "title": "Germany Dortmunnd Tamil Streetfestival livetelecast",
      "date": "02.09.2023",
      "timeFrom": "15:00",
      "timeTo": " 18:00",
      "description": "Germany Dortmund Tamil Streetfestival-23",
      "videoList": [{ "youtubeVideoID": "649LoYc1QHE" }, { "youtubeVideoID": "0" }]
    },
    {
      "label": "Stream - 01",
      "title": "Germany Hamm Srikamadchi Theer livetelecast",
      "date": "18.06.2023",
      "timeFrom": "9:30",
      "timeTo": " 12:30",
      "description": "Germany SRI KAMADCHI AMPAL THEER23",
      "videoList": [{ "youtubeVideoID": "FEYPnrp-Pg8" }, { "youtubeVideoID": "0" }]
    },
    {
      "label": "Stream - 01",
      "title": "Germany Srinavathurgadevi Tempel Newyear Poya livetelecast",
      "date": "01.01.2023",
      "timeFrom": "12:30",
      "timeTo": " 13:30",
      "description": "Germany Srinavathurgadevi Tempel -hünefeldstr63b-42285Wuppertal ",
      "videoList": [{ "youtubeVideoID": "Xvt7vPnIZjw" }, { "youtubeVideoID": "0" }]
    },
    {
      "label": "Stream - 02",
      "title": "Germany  Gummersbach Kurinchikumaran Tempel Theer Livetelecast",
      "date": "17.07.2022",
      "timeFrom": "9:30",
      "timeTo": " 12:30",
      "description": " Industriestraße 7- 51643 Gummersbach 02261 5015964 ",
      "videoList": [{ "youtubeVideoID":"E1vUX5dwXqk" }, { "youtubeVideoID": "1" }]
    },
    {
      "label": "Stream - 01",
      "title": "Kugatharan & Shajera wedding livetelecast",
      "date": "05.11.2022",
      "timeFrom": "11:30",
      "timeTo": " 13:30",
      "description": "Germany Srinavathurgadevi Tempel -hünefeldstr63b-42285Wuppertal ",
      "videoList": [{ "youtubeVideoID": "1zXKyrml8Qg" }, { "youtubeVideoID": "0" }]
    },
    {
      "label": "Stream - 01",
      "title": "Anejan Jeyam & Anuji Saravanabavan wedding livetelecast",
      "date": "16.07.2022",
      "timeFrom": "10:00",
      "timeTo": " 13:00",
      "description": "YNS Arena Halle- Germany Eisenwerkstr. 4 · 58332 Schwelm ",
      "videoList": [{ "youtubeVideoID": "zPi27rzXp6U" }, { "youtubeVideoID": "0" }]
    },
    {
      "label": "Stream - 02",
      "title": "Germany  Gummersbach Kurinchikumaran Tempel Theer Livetelecast",
      "date": "17.07.2022",
      "timeFrom": "9:30",
      "timeTo": " 12:30",
      "description": " Industriestraße 7- 51643 Gummersbach 02261 5015964 ",
      "videoList": [{ "youtubeVideoID":"E1vUX5dwXqk" }, { "youtubeVideoID": "1" }]
    },        
    {
      "label": "Stream - 02",
      "title": "Germany Hamm Theer livetelecast",
      "date": "26.06.2022",
      "timeFrom": "9:30",
      "timeTo": " 12:30",
      "description": " Germany Hamm Sri sangara Kamadchiampal Temple ",
      "videoList": [{ "youtubeVideoID": "gJ4hUUN-1cE" }, { "youtubeVideoID": "5Oc8CPRGEC0" },{ "youtubeVideoID": "gXYB4fBY1z0" },{ "youtubeVideoID": "GfCRjSM1FyU" },{ "youtubeVideoID": "ZHbwZ0EFbuk" }]
    },
    {
      "label": "Stream - 03",
      "title": "Shoban Prabagaran & Kaveetheeni Kaneen from Malasiya Wedding late livetelecast",
      "date": "26.06.2022",
      "timeFrom": "12:30",
      "timeTo": " 14:00",
      "description": " Malasiya Murugan Kovel ",
      "videoList": [{ "youtubeVideoID": "INiO-3ikBd8" }, { "youtubeVideoID": "4" }]
    },        
    {
      "label": "Stream - 04",
      "title": "Shoban Prabagaran  from Australia & Kaveetheeni Kaneen- Reception livetelecast(Origanal-Video)",
      "date": "02.04.2022",
      "timeFrom": "17:30",
      "timeTo": " 20:00",
      "description": " Germany Wuppertal Westfalenweg88-42111Wuppertal ",
      "videoList": [{ "youtubeVideoID": "nIqElO6AFTk" }, { "youtubeVideoID": "hhCuFIQj3PA" }]
    },            
    {
      "label": "Stream - 05",
      "title": "Shoban Prabagaran  from Australia & Kaveetheeni Kaneen- Registration and Temple Pooja  livetelecast",
      "date": "22.03.2022",
      "timeFrom": "10:45 and 19:00",
      "timeTo": "11:45 and 20:00",
      "description": " Germany Wuppertal and Sri Navathurgathevi Temple Wuppertal ",
      "videoList": [{ "youtubeVideoID": "uWSZp4pAkcY" }, { "youtubeVideoID": "hhCuFIQj3PA" }]
    },
    {
      "label": "Stream - 06",
      "title": "Shoban Prabagaran  from Australia & Kaveetheeni Kaneen- Reception livetelecast(Origanal-Video)",
      "date": "02.04.2022",
      "timeFrom": "17:30",
      "timeTo": " 20:00",
      "description": " Germany Wuppertal Westfalenweg88-42111Wuppertal ",
      "videoList": [{ "youtubeVideoID": "nIqElO6AFTk" }, { "youtubeVideoID": "hhCuFIQj3PA" }]
    },        
    {
      "label": "Stream - 07",
      "title": "Seanghon and Athina WEDDING livetelecast",
      "date": "06.04.2022",
      "timeFrom": "9:30",
      "timeTo": " 11:30",
      "description": " Germany Dortmund Siven Temple ",
      "videoList": [{ "youtubeVideoID": "2fsey69SSAU" }, { "youtubeVideoID": "ELA2BUKorYg" }]
    },    
    {
      "label": "Stream - 08",
      "title": "Germany Hamm Sugirthan Alakesakurukkal and Malikarchchuna Paskarakurukkal Wedding livetelecast",
      "date": "11.02.2022",
      "timeFrom": "11:00",
      "timeTo": "13:00",
      "description": " Germany Hamm Kamadchi Kalasara Mandapam ",
      "videoList": [{ "youtubeVideoID": "roisisLzJoM" }, { "youtubeVideoID": "cH-Gz-kEqIs" }]
    },    
    {
      "label": "Stream - 09",
      "title": "Germany Hamm Kamadchi Kalasara Mandapa livetelecast",
      "date": "06.02.2022",
      "timeFrom": "11:00",
      "timeTo": "12:30",
      "description": " Germany Hamm Opening Ceremony",
      "videoList": [{ "youtubeVideoID": "kRJ8i4rX9UI" }, { "youtubeVideoID": "84CRRTT-0G8" }]
    },    
    {
      "label": "Stream - 10",
      "title": "Germany Ruban and Shakana Wedding livetelecadt",
      "date": "23.08.2021",
      "timeFrom": "10:30",
      "timeTo": "13:00",
      "description": " Srinavthurgadevi tempel wuppertal Germany",
      "videoList": [{ "youtubeVideoID": "i9GyJlxKwNA" }, { "youtubeVideoID": "84CRRTT-0G8" }, { "youtubeVideoID": "JrpgGZH6U_c" }, { "youtubeVideoID": "ol1KNZ32CfY" }, { "youtubeVideoID": "l5pSkQZx_Ok" }]
    },
    {
      "label": "Stream - 11",
      "title": "Germany Gaurav Punj and Tarandeep Kaur Reception Wedding",
      "date": "28.07.2021",
      "timeFrom": "17:00",
      "timeTo": "19:00",
      "description": " Dortmund Flamingo Restaurant",
      "videoList": [{ "youtubeVideoID": "y9NDwUmOkZU" }, { "youtubeVideoID": "WVpk6iHLPhw" }]
    },
    {
      "label": "Stream - 12",
      "title": "Germany Hamm Theer Livetelcast",
      "date": "11.07.2021",
      "timeFrom": "09:00",
      "timeTo": "13:00",
      "description": "Hamm Kovil Livetelecast",
      "videoList": [{ "youtubeVideoID": "i7u_dlC5fgI" }]
    },
    {
      "label": "Stream - 13",
      "title": "Wuppertal Kovel",
      "date": "15.05.2021",
      "timeFrom": "11:00",
      "timeTo": "15:00",
      "description": "Wuppertal-Alaingara Pusai",
      "videoList": [{ "youtubeVideoID": "gvV0PNnNmxA" }]
    },
    {
      "label": "Stream - 14",
      "title": "Anand and Lakshmi Wedding",
      "date": "01.07.2021",
      "timeFrom": "09:00",
      "timeTo": "13:00",
      "description": "Hamm Kovil Wedding",
      "videoList": [{ "youtubeVideoID": "cKv-swjhd8I" }, { "youtubeVideoID": "xqDsCm8X8ow" }]
    },
    {
      "label": "Stream - 15",
      "title": "Jenny and Lavan-Wedding-2",
      "date": "24.05.2021",
      "timeFrom": "10:00",
      "timeTo": "12:00",
      "description": "We like to thank you in advance for joining us virtually for our Hindu wedding ceremony",
      "videoList": [{ "youtubeVideoID": "hWDspyxKrvQ" }]
    },
    {
      "label": "Stream - 16",
      "title": "Wuppertal Kovel",
      "date": "15.05.2021",
      "timeFrom": "11:00",
      "timeTo": "03:00",
      "description": "",
      "videoList": [{ "youtubeVideoID": "rd4Ey6alhkg" }]
    }
  ]
}
